pmgmssql/__init__.py
pmgmssql/tools.py
pmgmssql-0.1.2.dist-info/LICENSE
pmgmssql-0.1.2.dist-info/METADATA
pmgmssql-0.1.2.dist-info/WHEEL
pmgmssql-0.1.2.dist-info/top_level.txt
pmgmssql-0.1.2.dist-info/RECORD
